TensorState/__init__.py
TensorState/_TensorState.pyx
TensorState/Layers.py
TensorState/models/__init__.py
TensorState/models/LeNet.py
TensorState/models/MobileNetV2.py
TensorState/States.py
TensorState/TensorState.py
TensorState/__init__.py
TensorState/_TensorState.cp39-win_amd64.pyd
TensorState/_TensorState.cpp
TensorState/_TensorState.pyx
TensorState/Layers.py
TensorState/models/__init__.py
TensorState/models/LeNet.py
TensorState/models/MobileNetV2.py
TensorState/States.py
TensorState/TensorState.py
tensorstate-0.4.0.dist-info/LICENSE
tensorstate-0.4.0.dist-info/METADATA
tensorstate-0.4.0.dist-info/WHEEL
tensorstate-0.4.0.dist-info/RECORD
