Metadata-Version: 2.1
Name: tensorstate
Version: 0.4.0
Summary: 
Author: Nicholas-Schaub
Author-email: nicholas.j.schaub@gmail.com
Requires-Python: >=3.8.1,<4.0.0
Classifier: Programming Language :: Python :: 3
Classifier: Programming Language :: Python :: 3.9
Classifier: Programming Language :: Python :: 3.10
Classifier: Programming Language :: Python :: 3.11
Requires-Dist: numcodecs (>=0.11.0,<0.12.0)
Requires-Dist: numpy (>=1.24.2,<2.0.0)
Requires-Dist: zarr (>=2.14.2,<3.0.0)
